{
  "meta": {
    "基金代號": "00932",
    "基金名稱": "兆豐台灣ESG永續高股息等權重ETF證券投資信託基金",
    "總市值": 373,
    "排碳大戶家數": 24,
    "排碳大戶佔比": 28.57,
    "排碳大戶總碳排量": 49279304,
    "使用燃煤家數": 5
  },
  "companies": [
    {
      "公司": "聯電",
      "產業分類": "半導體業",
      "溫室氣體排放量（公噸二氧化碳當量）": "1,491,934",
      "淨零目標年": "2050",
      "2030 年減量目標設定": "42.0%",
      "SBTi 承諾": "符合1.5°C目標",
      ">> 雷達圖數據": "",
      "2030年溫室氣體絕對減量目標": "2",
      "2030年再生能源使用率目標": "3",
      "2030年能源效率進步目標": "3",
      "2024年再生能源使用率": "3",
      "2022-2024年能源效率進步率": "3",
      "範疇三及減量策略": "2",
      "有具體減量策略": "自主減碳、投資淨零技術、採用再生能源",
      "範疇三揭露": "✅",
      "範疇三減量規劃": "✅",
      "近三年能效進步率": "21.5%",
      "節能目標設定": "30.00%",
      "再生能源使用率": "17.1%",
      "再生能源設置容量": "14,000",
      "是否完成用電大戶再生能源設置義務": "",
      "中期再生能源目標設定": "0.5",
      "RE100 承諾": "✅",
      "燃煤使用量（公噸）": "0",
      "代表縣市": "台南市",
      "事業統編": "47217677",
      "公司全名": "聯華電子股份有限公司"
    },
    {
      "公司": "力成",
      "產業分類": "半導體業",
      "溫室氣體排放量（公噸二氧化碳當量）": "347,265",
      "淨零目標年": "2050",
      "2030 年減量目標設定": "15.0%",
      "SBTi 承諾": "❌",
      ">> 雷達圖數據": "",
      "2030年溫室氣體絕對減量目標": "1",
      "2030年再生能源使用率目標": "1",
      "2030年能源效率進步目標": "1",
      "2024年再生能源使用率": "0",
      "2022-2024年能源效率進步率": "3",
      "範疇三及減量策略": "2",
      "有具體減量策略": "設備汰換、參數優化、照明汰換、建置太陽能、購買綠電",
      "範疇三揭露": "✅",
      "範疇三減量規劃": "✅",
      "近三年能效進步率": "3.4%",
      "節能目標設定": "1.00%",
      "再生能源使用率": "3.4%",
      "再生能源設置容量": "",
      "是否完成用電大戶再生能源設置義務": "",
      "中期再生能源目標設定": "0.15",
      "RE100 承諾": "❌",
      "燃煤使用量（公噸）": "0",
      "代表縣市": "新竹縣",
      "事業統編": "16082267",
      "公司全名": "力成科技股份有限公司"
    },
    {
      "公司": "榮剛",
      "產業分類": "鋼鐵業",
      "溫室氣體排放量（公噸二氧化碳當量）": "196,134",
      "淨零目標年": "2050",
      "2030 年減量目標設定": "",
      "SBTi 承諾": "❌",
      ">> 雷達圖數據": "",
      "2030年溫室氣體絕對減量目標": "0",
      "2030年再生能源使用率目標": "0",
      "2030年能源效率進步目標": "2",
      "2024年再生能源使用率": "0",
      "2022-2024年能源效率進步率": "0",
      "範疇三及減量策略": "2",
      "有具體減量策略": "製程簡化、設備節能、再生能源、低碳燃料、廢鋼回收",
      "範疇三揭露": "✅",
      "範疇三減量規劃": "✅",
      "近三年能效進步率": "-4.3%",
      "節能目標設定": "1.50%",
      "再生能源使用率": "0.7%",
      "再生能源設置容量": "3,158",
      "是否完成用電大戶再生能源設置義務": "",
      "中期再生能源目標設定": "",
      "RE100 承諾": "❌",
      "燃煤使用量（公噸）": "0"
    },
    {
      "公司": "頎邦",
      "產業分類": "半導體業",
      "溫室氣體排放量（公噸二氧化碳當量）": "140,563",
      "淨零目標年": "",
      "2030 年減量目標設定": "23.0%",
      "SBTi 承諾": "❌",
      ">> 雷達圖數據": "",
      "2030年溫室氣體絕對減量目標": "1",
      "2030年再生能源使用率目標": "0",
      "2030年能源效率進步目標": "1",
      "2024年再生能源使用率": "0",
      "2022-2024年能源效率進步率": "0",
      "範疇三及減量策略": "0",
      "有具體減量策略": "耗能設備汰舊換新、照明管理、再生能源使用、可視化管理、強化員工節能意識",
      "範疇三揭露": "✅",
      "範疇三減量規劃": "❌",
      "近三年能效進步率": "-2804.5%",
      "節能目標設定": "1.00%",
      "再生能源使用率": "0.2%",
      "再生能源設置容量": "",
      "是否完成用電大戶再生能源設置義務": "✅",
      "中期再生能源目標設定": "",
      "RE100 承諾": "❌",
      "燃煤使用量（公噸）": "0"
    },
    {
      "公司": "敬鵬",
      "產業分類": "電子業",
      "溫室氣體排放量（公噸二氧化碳當量）": "61,476",
      "淨零目標年": "2050",
      "2030 年減量目標設定": "25.0%",
      "SBTi 承諾": "❌",
      ">> 雷達圖數據": "",
      "2030年溫室氣體絕對減量目標": "1",
      "2030年再生能源使用率目標": "2",
      "2030年能源效率進步目標": "3",
      "2024年再生能源使用率": "2",
      "2022-2024年能源效率進步率": "3",
      "範疇三及減量策略": "2",
      "有具體減量策略": "提升能源效率、使用再生能源、低碳技術創新、推動循環經濟、供應鏈減碳",
      "範疇三揭露": "✅",
      "範疇三減量規劃": "✅",
      "近三年能效進步率": "6.8%",
      "節能目標設定": "5.00%",
      "再生能源使用率": "13.0%",
      "再生能源設置容量": "",
      "是否完成用電大戶再生能源設置義務": "",
      "中期再生能源目標設定": "0.3",
      "RE100 承諾": "",
      "燃煤使用量（公噸）": "0",
      "代表縣市": "桃園市",
      "事業統編": "43816068",
      "公司全名": "敬鵬工業股份有限公司"
    },
    {
      "公司": "矽格",
      "產業分類": "半導體業",
      "溫室氣體排放量（公噸二氧化碳當量）": "42,217",
      "淨零目標年": "2050",
      "2030 年減量目標設定": "14.0%",
      "SBTi 承諾": "❌",
      ">> 雷達圖數據": "",
      "2030年溫室氣體絕對減量目標": "1",
      "2030年再生能源使用率目標": "2",
      "2030年能源效率進步目標": "2",
      "2024年再生能源使用率": "0",
      "2022-2024年能源效率進步率": "1",
      "範疇三及減量策略": "2",
      "有具體減量策略": "智慧工廠、節約能源、再生能源、製程改善、設備汰換",
      "範疇三揭露": "✅",
      "範疇三減量規劃": "✅",
      "近三年能效進步率": "1.3%",
      "節能目標設定": "1.50%",
      "再生能源使用率": "2.9%",
      "再生能源設置容量": "",
      "是否完成用電大戶再生能源設置義務": "",
      "中期再生能源目標設定": "0.3",
      "RE100 承諾": "❌",
      "燃煤使用量（公噸）": "0",
      "代表縣市": "新竹縣",
      "事業統編": "23218022",
      "公司全名": "矽格股份有限公司"
    },
    {
      "公司": "欣銓",
      "產業分類": "半導體業",
      "溫室氣體排放量（公噸二氧化碳當量）": "0",
      "淨零目標年": "2050",
      "2030 年減量目標設定": "20.0%",
      "SBTi 承諾": "❌",
      ">> 雷達圖數據": "",
      "2030年溫室氣體絕對減量目標": "1",
      "2030年再生能源使用率目標": "1",
      "2030年能源效率進步目標": "1",
      "2024年再生能源使用率": "2",
      "2022-2024年能源效率進步率": "3",
      "範疇三及減量策略": "1",
      "有具體減量策略": "提升能源效率、使用再生能源、低碳技術轉型、低碳服務研發",
      "範疇三揭露": "✅",
      "範疇三減量規劃": "",
      "近三年能效進步率": "5.2%",
      "節能目標設定": "1.00%",
      "再生能源使用率": "10.4%",
      "再生能源設置容量": "1,535",
      "是否完成用電大戶再生能源設置義務": "✅",
      "中期再生能源目標設定": "0.2",
      "RE100 承諾": "✅",
      "燃煤使用量（公噸）": "0"
    },
    {
      "公司": "廣達",
      "產業分類": "電子業",
      "溫室氣體排放量（公噸二氧化碳當量）": "30,071",
      "淨零目標年": "2050",
      "2030 年減量目標設定": "42.0%",
      "SBTi 承諾": "承諾設定科學基礎目標",
      ">> 雷達圖數據": "",
      "2030年溫室氣體絕對減量目標": "2",
      "2030年再生能源使用率目標": "2",
      "2030年能源效率進步目標": "0",
      "2024年再生能源使用率": "3",
      "2022-2024年能源效率進步率": "0",
      "範疇三及減量策略": "1",
      "有具體減量策略": "推動節能改善、再生能源導入、綠色供應鏈、低碳產品設計",
      "範疇三揭露": "❌",
      "範疇三減量規劃": "✅",
      "近三年能效進步率": "-2.5%",
      "節能目標設定": "",
      "再生能源使用率": "47.5%",
      "再生能源設置容量": "",
      "是否完成用電大戶再生能源設置義務": "",
      "中期再生能源目標設定": "0.5",
      "RE100 承諾": "❌",
      "燃煤使用量（公噸）": "0",
      "代表縣市": "桃園市",
      "事業統編": "22822281",
      "公司全名": "廣達電腦股份有限公司"
    },
    {
      "公司": "三芳",
      "產業分類": "石化業",
      "溫室氣體排放量（公噸二氧化碳當量）": "29,846",
      "淨零目標年": "",
      "2030 年減量目標設定": "18.0%",
      "SBTi 承諾": "承諾設定科學基礎目標",
      ">> 雷達圖數據": "",
      "2030年溫室氣體絕對減量目標": "1",
      "2030年再生能源使用率目標": "2",
      "2030年能源效率進步目標": "1",
      "2024年再生能源使用率": "2",
      "2022-2024年能源效率進步率": "3",
      "範疇三及減量策略": "2",
      "有具體減量策略": "節能減廢、潔淨能源、綠色設計、價值鏈減碳、能源轉型",
      "範疇三揭露": "✅",
      "範疇三減量規劃": "✅",
      "近三年能效進步率": "100.0%",
      "節能目標設定": "1.00%",
      "再生能源使用率": "10.6%",
      "再生能源設置容量": "3,940",
      "是否完成用電大戶再生能源設置義務": "✅",
      "中期再生能源目標設定": "1",
      "RE100 承諾": "❌",
      "燃煤使用量（公噸）": "0",
      "代表縣市": "高雄市",
      "事業統編": "83387850",
      "公司全名": "三芳化學工業股份有限公司"
    },
    {
      "公司": "可成",
      "產業分類": "鋁製造業",
      "溫室氣體排放量（公噸二氧化碳當量）": "26,447",
      "淨零目標年": "2050",
      "2030 年減量目標設定": "46.2%",
      "SBTi 承諾": "符合1.5°C目標",
      ">> 雷達圖數據": "",
      "2030年溫室氣體絕對減量目標": "3",
      "2030年再生能源使用率目標": "2",
      "2030年能源效率進步目標": "2",
      "2024年再生能源使用率": "0",
      "2022-2024年能源效率進步率": "3",
      "範疇三及減量策略": "2",
      "有具體減量策略": "綠能投資、節能措施、製程優化、設備汰舊換新",
      "範疇三揭露": "✅",
      "範疇三減量規劃": "✅",
      "近三年能效進步率": "53.6%",
      "節能目標設定": "1.50%",
      "再生能源使用率": "4.9%",
      "再生能源設置容量": "1,122",
      "是否完成用電大戶再生能源設置義務": "",
      "中期再生能源目標設定": "0.6",
      "RE100 承諾": "❌",
      "燃煤使用量（公噸）": "0",
      "代表縣市": "台南市",
      "事業統編": "69905810",
      "公司全名": "可成科技股份有限公司"
    }
  ]
}